strplus/__init__.py
strplus/cases.py
strplus/functions.py
strplus/strplus.py
strplus-1.0.10.dist-info/METADATA
strplus-1.0.10.dist-info/WHEEL
strplus-1.0.10.dist-info/LICENSE
strplus-1.0.10.dist-info/RECORD
